django_ticketoffice
