Metadata-Version: 1.1
Name: django-ticketoffice
Version: 0.2
Summary: One-shot authentication (temporary credentials) utilities for Django.
Home-page: https://django-ticketoffice.readthedocs.org/
Author: Benoît Bryon
Author-email: benoit@marmelune.net
License: BSD
Keywords: authentication
Platform: UNKNOWN
Classifier: Development Status :: 3 - Alpha
Classifier: License :: OSI Approved :: BSD License
Classifier: Programming Language :: Python :: 2.7
Classifier: Framework :: Django
